devops_tools-0.1.dist-info/DESCRIPTION.rst
devops_tools-0.1.dist-info/METADATA
devops_tools-0.1.dist-info/RECORD
devops_tools-0.1.dist-info/WHEEL
devops_tools-0.1.dist-info/entry_points.txt
devops_tools-0.1.dist-info/metadata.json
devops_tools-0.1.dist-info/top_level.txt
devopstools/__init__.py
devopstools/ansible_docker.py
devopstools/docker_cli.py
devopstools/general.py
devopstools/generator.py
devopstools/logging.conf
devopstools/generator/.dockerignore
devopstools/generator/.gitignore
devopstools/generator/Dockerfile
devopstools/generator/README.md
devopstools/generator/docker-compose/docker-compose.yml
devopstools/generator/docker-compose/env.build.ci.main
devopstools/generator/docker-compose/env.build.dev.main
devopstools/generator/files/docker-entrypoint.sh
devopstools/generator/tests/goss.yaml
devopstools/git-helper/changelog.sh
devopstools/git-helper/git_helper.sh
devopstools/git-helper/git_helper_docker.sh
devopstools/git-helper/inc_sem_ver.sh
