Metadata-Version: 2.0
Name: devops-tools
Version: 0.1
Summary: Devops Tools
Home-page: UNKNOWN
Author: Pablo Venegas
Author-email: pablo.venegas@gmail.com
License: MIT
Keywords: devops docker
Platform: UNKNOWN
Classifier: Development Status :: 1 - Planning
Classifier: Programming Language :: Python
Requires-Dist: PyYAML
Requires-Dist: docker-py
Requires-Dist: dockerpty
